<SystemSettings>
    <NumberMTU>1</NumberMTU>
    <NumberSpyder>1</NumberSpyder>

    <DemoMode>0</DemoMode>
    <NumberDisplay>1</NumberDisplay>
    <DateTime>
        <UseServer>1</UseServer>
        <ServerAddress>pool.ntp.org</ServerAddress>
        <UseDLST>1</UseDLST>
        <InDLST>0</InDLST>
        <TimeZone>-5</TimeZone>
    </DateTime>

    <ZipCode>29401</ZipCode>
    <WxUseLatLon>0</WxUseLatLon>
    <WxLat>3282</WxLat>
    <WxLon>-7986</WxLon>
    <Configuration>
        <SystemType>0</SystemType>
        <MTUType1>0</MTUType1>
        <MTUType2>0</MTUType2>
        <MTUType3>0</MTUType3>
        <MTUType4>0</MTUType4>
    </Configuration>

    <USNAP>
        <USNAPType1>2</USNAPType1>
        <USNAPType2>0</USNAPType2>
    </USNAP>

    <MTUPollingDelay>1</MTUPollingDelay>

    <MTUs>
        <MTU>
            <MTUNumber>1</MTUNumber>
            <MTUID>130750</MTUID>
            <MTUDescription></MTUDescription>
            <PowerCalibrationFactor>1000</PowerCalibrationFactor>
            <VoltageCalibrationFactor>1000</VoltageCalibrationFactor>
            <UseTCP>0</UseTCP>
            <MTUIP>0.0.0.0</MTUIP>
        </MTU>
        <MTU>
            <MTUNumber>2</MTUNumber>
            <MTUID>000000</MTUID>
            <MTUDescription></MTUDescription>
            <PowerCalibrationFactor>1000</PowerCalibrationFactor>
            <VoltageCalibrationFactor>1000</VoltageCalibrationFactor>
            <UseTCP>0</UseTCP>
            <MTUIP>0.0.0.0</MTUIP>
        </MTU>
        <MTU>
            <MTUNumber>3</MTUNumber>
            <MTUID>000000</MTUID>
            <MTUDescription></MTUDescription>
            <PowerCalibrationFactor>1000</PowerCalibrationFactor>
            <VoltageCalibrationFactor>1000</VoltageCalibrationFactor>
            <UseTCP>0</UseTCP>
            <MTUIP>0.0.0.0</MTUIP>
        </MTU>
        <MTU>
            <MTUNumber>4</MTUNumber>
            <MTUID>000000</MTUID>
            <MTUDescription></MTUDescription>
            <PowerCalibrationFactor>1000</PowerCalibrationFactor>
            <VoltageCalibrationFactor>1000</VoltageCalibrationFactor>
            <UseTCP>0</UseTCP>
            <MTUIP>0.0.0.0</MTUIP>
        </MTU>

        <PEUAT>10</PEUAT>
        <PVAT>10</PVAT>

    </MTUs>

    <Gateway>
        <GatewayID>26059D</GatewayID>
        <GatewayDescription></GatewayDescription>
    </Gateway>


    <Displays>
        <DisplaySettings>
            <BacklightUnderPower>60</BacklightUnderPower>
            <BacklightUnderBattery>40</BacklightUnderBattery>
            <BacklightTimer>30</BacklightTimer>
            <ScrollTimer>5</ScrollTimer>
            <SleepTimer>120</SleepTimer>
            <RealTimeUseScreen>TRUE</RealTimeUseScreen>
            <RecentUsageScreen>TRUE</RecentUsageScreen>
            <MonthToDateScreen>TRUE</MonthToDateScreen>
            <MonthlyProjectionScreen>TRUE</MonthlyProjectionScreen>
            <VoltageScreen>TRUE</VoltageScreen>
            <KWDetailScreen>FALSE</KWDetailScreen>
            <SpendingDetailTdyScreen>FALSE</SpendingDetailTdyScreen>
            <CO2TodayScreen>FALSE</CO2TodayScreen>
            <MultiPanel1Screen>FALSE</MultiPanel1Screen>
            <MultiPanel2Screen>FALSE</MultiPanel2Screen>
            <Contrast>47</Contrast>
        </DisplaySettings>

        <Display>
            <DisplayNumber>1</DisplayNumber>
            <DisplayID>307F38</DisplayID>
            <DisplayDescription></DisplayDescription>
        </Display>
        <Display>
            <DisplayNumber>2</DisplayNumber>
            <DisplayID>000000</DisplayID>
            <DisplayDescription></DisplayDescription>
        </Display>
        <Display>
            <DisplayNumber>3</DisplayNumber>
            <DisplayID>000000</DisplayID>
            <DisplayDescription></DisplayDescription>
        </Display>
        <Display>
            <DisplayNumber>4</DisplayNumber>
            <DisplayID>000000</DisplayID>
            <DisplayDescription></DisplayDescription>
        </Display>


    </Displays>


    <Thermostats>
        <NumberIPT>0</NumberIPT>
        <Thermostat>
            <IPTNumber>1</IPTNumber>
            <IPTAddress>0.0.0.0</IPTAddress>
            <IPTDescription></IPTDescription>
            <RTAType>0</RTAType>
        </Thermostat>
        <Thermostat>
            <IPTNumber>2</IPTNumber>
            <IPTAddress>0.0.0.0</IPTAddress>
            <IPTDescription></IPTDescription>
            <RTAType>0</RTAType>
        </Thermostat>
        <StatRefresh>5</StatRefresh>
    </Thermostats>

    <CarbonCost>155</CarbonCost>

    <NetworkSettings>
        <UseDHCP>1</UseDHCP>
        <IPAddress>141.212.11.148</IPAddress>
        <SubnetMask>255.255.255.0</SubnetMask>
        <GatewayAddress>141.212.11.1</GatewayAddress>
        <PrimaryDNSServer>141.213.4.4</PrimaryDNSServer>
        <SecondaryDNSServer>141.213.15.4</SecondaryDNSServer>
        <NetBiosName>TED6000        </NetBiosName>
        <HTTPPort>80</HTTPPort>
        <HTTPSPort>443</HTTPSPort>

    </NetworkSettings>

    <Username>admin</Username>
    <PasswordAll>0</PasswordAll>
    <PasswordConf>0</PasswordConf>
    <ThirdPartyActivated>0</ThirdPartyActivated>

</SystemSettings>